pywinmake/__init__.py
pywinmake/__version__.py
pywinmake/models.py
pywinmake/builders/__init__.py
pywinmake/builders/cmake_builder.py
pywinmake/builders/meta_builder.py
pywinmake/builders/msb_builder.py
pywinmake/dev_env/__init__.py
pywinmake/dev_env/host_config.py
pywinmake/dev_env/vs_env.py
pywinmake/package/__init__.py
pywinmake/package/build_tools.py
pywinmake/package/fetcher.py
pywinmake/package/package.py
pywinmake/package/patcher.py
pywinmake/package/versioner.py
pywinmake/utils/__init__.py
pywinmake/utils/logger.py
pywinmake/utils/process.py
pywinmake/utils/singleton.py
pywinmake-0.3.1.dist-info/METADATA
pywinmake-0.3.1.dist-info/WHEEL
pywinmake-0.3.1.dist-info/top_level.txt
pywinmake-0.3.1.dist-info/RECORD
